wagtail_feathers/__init__.py
wagtail_feathers/apps.py
wagtail_feathers/blocks.py
wagtail_feathers/context_processors.py
wagtail_feathers/factories.py
wagtail_feathers/fields.py
wagtail_feathers/filters.py
wagtail_feathers/forms.py
wagtail_feathers/helpers.py
wagtail_feathers/mixins.py
wagtail_feathers/panels.py
wagtail_feathers/struct_values.py
wagtail_feathers/styles.py
wagtail_feathers/themes.py
wagtail_feathers/version.py
wagtail_feathers/views.py
wagtail_feathers/wagtail_hooks.py
wagtail_feathers/widgets.py
wagtail_feathers/fixtures/sample_taxonomy.json
wagtail_feathers/management/__init__.py
wagtail_feathers/management/commands/__init__.py
wagtail_feathers/management/commands/create_sample_taxonomy.py
wagtail_feathers/management/commands/manage_categories.py
wagtail_feathers/management/commands/tailwind_source.py
wagtail_feathers/management/commands/themes.py
wagtail_feathers/migrations/0001_initial.py
wagtail_feathers/migrations/__init__.py
wagtail_feathers/models/__init__.py
wagtail_feathers/models/author.py
wagtail_feathers/models/base.py
wagtail_feathers/models/errors.py
wagtail_feathers/models/faq.py
wagtail_feathers/models/geographic.py
wagtail_feathers/models/inline.py
wagtail_feathers/models/navigation.py
wagtail_feathers/models/person.py
wagtail_feathers/models/settings.py
wagtail_feathers/models/social.py
wagtail_feathers/models/specialized_pages.py
wagtail_feathers/models/taxonomy.py
wagtail_feathers/models/utils.py
wagtail_feathers/static/.DS_Store
wagtail_feathers/static/css/wagtail_feathers_admin.css
wagtail_feathers/static/images/placeholder-image.webp
wagtail_feathers/static/js/wagtail_feathers_admin.js
wagtail_feathers/templates/wagtail_feathers/admin/category_add_child.html
wagtail_feathers/templates/wagtail_feathers/admin/category_move.html
wagtail_feathers/templates/wagtail_feathers/admin/generic/chooser/classifier_chooser.html
wagtail_feathers/templates/wagtail_feathers/blocks/_nested_navigation_link_block.html
wagtail_feathers-1.0b11.dist-info/licenses/LICENSE
wagtail_feathers-1.0b11.dist-info/WHEEL
wagtail_feathers-1.0b11.dist-info/METADATA
wagtail_feathers-1.0b11.dist-info/RECORD
