Metadata-Version: 2.4
Name: wagtail-feathers
Version: 1.0b11
Summary: A comprehensive Wagtail CMS extension providing theming and foundational features.
Keywords: wagtail,django,cms,content,management,taxonomy,navigation,themes
Author-email: Maxime Decooman <maxime@softquantum.com>
Maintainer-email: Maxime Decooman <maxime@softquantum.com>
Requires-Python: >=3.11
Classifier: Development Status :: 4 - Beta
Classifier: Environment :: Web Environment
Classifier: Framework :: Django
Classifier: Framework :: Django :: 5.2
Classifier: Framework :: Wagtail
Classifier: Framework :: Wagtail :: 7
Classifier: Intended Audience :: Developers
Classifier: License :: OSI Approved :: BSD License
Classifier: Operating System :: OS Independent
Classifier: Programming Language :: Python :: 3
Classifier: Programming Language :: Python :: 3.11
Classifier: Programming Language :: Python :: 3.12
Classifier: Programming Language :: Python :: 3.13
Classifier: Topic :: Internet :: WWW/HTTP :: Dynamic Content
Classifier: Topic :: Software Development :: Libraries :: Python Modules
License-File: LICENSE
Requires-Dist: Wagtail>=6.4
Requires-Dist: wagtail-markdown>=0.10.0
Requires-Dist: django-countries[pyuca]>=7.6.1
Requires-Dist: django-extensions>=3.2.0
Requires-Dist: python-decouple>=3.8
Requires-Dist: pytest>=8.0.0 ; extra == "dev"
Requires-Dist: pytest-django>=4.8.0 ; extra == "dev"
Requires-Dist: pytest-cov>=4.0.0 ; extra == "dev"
Requires-Dist: factory-boy>=3.3.0 ; extra == "dev"
Requires-Dist: ruff>=0.1.0 ; extra == "dev"
Requires-Dist: tox>=4.0.0 ; extra == "dev"
Requires-Dist: wagtail-localize>=1.9 ; extra == "localize"
Requires-Dist: psycopg>=3.2 ; extra == "production"
Project-URL: Home, https://github.com/softquantum/wagtail-feathers
Project-URL: Issues, https://github.com/softquantum/wagtail-feathers/issues
Provides-Extra: dev
Provides-Extra: localize
Provides-Extra: production
